apispec_flask_restful/__init__.py
apispec_flask_restful/flask_restful.py
apispec_flask_restful-0.1.dist-info/DESCRIPTION.rst
apispec_flask_restful-0.1.dist-info/METADATA
apispec_flask_restful-0.1.dist-info/RECORD
apispec_flask_restful-0.1.dist-info/WHEEL
apispec_flask_restful-0.1.dist-info/metadata.json
apispec_flask_restful-0.1.dist-info/top_level.txt
